e84_geoai_common/__init__.py
e84_geoai_common/debugging.py
e84_geoai_common/geojson.py
e84_geoai_common/geometry.py
e84_geoai_common/py.typed
e84_geoai_common/util.py
e84_geoai_common/llm/__init__.py
e84_geoai_common/llm/batch.py
e84_geoai_common/llm/extraction.py
e84_geoai_common/llm/py.typed
e84_geoai_common/llm/core/__init__.py
e84_geoai_common/llm/core/agent.py
e84_geoai_common/llm/core/llm.py
e84_geoai_common/llm/models/__init__.py
e84_geoai_common/llm/models/claude.py
e84_geoai_common/llm/models/nova.py
e84_geoai_common/llm/models/converse/__init__.py
e84_geoai_common/llm/models/converse/converse.py
e84_geoai_common/llm/models/converse/data_content_types.py
e84_geoai_common/llm/models/converse/msg_types.py
e84_geoai_common/llm/models/converse/response_types.py
e84_geoai_common/llm/models/converse/tool_use_types.py
e84_geoai_common/llm/tests/__init__.py
e84_geoai_common/llm/tests/mock_bedrock.py
e84_geoai_common/llm/tests/mock_bedrock_runtime.py
e84_geoai_common/llm/tests/pydantic_compare.py
e84_geoai_common-0.0.6.dist-info/licenses/LICENSE
e84_geoai_common-0.0.6.dist-info/METADATA
e84_geoai_common-0.0.6.dist-info/WHEEL
e84_geoai_common-0.0.6.dist-info/top_level.txt
e84_geoai_common-0.0.6.dist-info/RECORD
