Metadata-Version: 2.4
Name: e84-geoai-common
Version: 0.0.6
Summary: Contains common Geospatial AI/ML code for Element 84 projects.
Author-email: Jason Gilman <jason@element84.com>
Maintainer-email: Jason Gilman <jason@element84.com>
License:                                  Apache License
Project-URL: Github, https://github.com/Element84/e84-geoai-common
Requires-Python: >=3.12
License-File: LICENSE
Requires-Dist: boto3>=1.35.20
Requires-Dist: boto3-stubs[bedrock,bedrock-runtime,s3]>=1.35.20
Requires-Dist: pydantic>=2.9.1
Requires-Dist: shapely>=2.0.6
Requires-Dist: types-shapely>=2.0.0.20240820
Requires-Dist: function_schema>=0.4.4
Requires-Dist: rich
Requires-Dist: mypy-boto3-bedrock-runtime>=1.37.0
Provides-Extra: debugging
Requires-Dist: folium>=0.17.0; extra == "debugging"
Provides-Extra: dev
Requires-Dist: pytest>=8.3.3; extra == "dev"
Requires-Dist: pytest-watch; extra == "dev"
Requires-Dist: ipykernel>=6.29.5; extra == "dev"
Requires-Dist: ruff>=0.6.8; extra == "dev"
Requires-Dist: pyright>=1.1.381; extra == "dev"
Requires-Dist: build>=1.2.2; extra == "dev"
Requires-Dist: pre-commit>=3.8.0; extra == "dev"
Requires-Dist: pre-commit-hooks>=4.6.0; extra == "dev"
Requires-Dist: moto[s3]>=5.0.0; extra == "dev"
Dynamic: license-file
